cylp-0.94.0.dist-info/RECORD
cylp-0.94.0.dist-info/WHEEL
cylp-0.94.0.dist-info/top_level.txt
cylp-0.94.0.dist-info/METADATA
cylp-0.94.0.dist-info/licenses/LICENSE
cylp-0.94.0.dist-info/licenses/AUTHORS
cylp/__init__.py
cylp/VERSION
cylp/py/Constants.py
cylp/py/__init__.py
cylp/py/PySolve.py
cylp/py/test_PySolve.py
cylp/py/utils/readSetcovering.py
cylp/py/utils/util.py
cylp/py/utils/sparseUtil.py
cylp/py/utils/__init__.py
cylp/py/modeling/__init__.py
cylp/py/modeling/CyLPModel.py
cylp/py/modeling/test_modeling.py
cylp/py/mip/NodeCompareBase.py
cylp/py/mip/CyLPCutGenerator.py
cylp/py/mip/__init__.py
cylp/py/mip/GomoryCutGenerator.py
cylp/py/mip/SimpleNodeCompare.py
cylp/py/pivots/WolfePivot.py
cylp/py/pivots/WolfePivotPE.py
cylp/py/pivots/LIFOPivot.py
cylp/py/pivots/DualPivotPythonBase.py
cylp/py/pivots/PositiveEdgeWolfePivot.py
cylp/py/pivots/MostFrequentPivot.py
cylp/py/pivots/DualDantzigPivot.py
cylp/py/pivots/DantzigPivot.py
cylp/py/pivots/PositiveEdgePivot.py
cylp/py/pivots/__init__.py
cylp/py/pivots/PivotPythonBase.py
cylp/py/QP/QP.py
cylp/py/QP/__init__.py
cylp/py/QP/QPSReader.py
cylp/py/QP/GQP.py
cylp/py/QP/QPGen.py
cylp/.dylibs/libClp.1.14.10.dylib
cylp/.dylibs/libClpSolver.1.14.10.dylib
cylp/.dylibs/libOsiClp.1.14.10.dylib
cylp/.dylibs/libCbcSolver.3.10.12.dylib
cylp/.dylibs/libOsi.1.13.11.dylib
cylp/.dylibs/libCbc.3.10.12.dylib
cylp/.dylibs/libCoinUtils.3.11.12.dylib
cylp/.dylibs/libCgl.1.10.9.dylib
cylp/cpp/ICglCutGeneratorBase.h
cylp/cpp/ICoinPackedMatrix.hpp
cylp/cpp/ICglCutGeneratorBase.cpp
cylp/cpp/ICoinIndexedVector.cpp
cylp/cpp/CyClpSimplex_api.h
cylp/cpp/ICbcNode.hpp
cylp/cpp/ICbc.cpp
cylp/cpp/IClpSimplex.cpp
cylp/cpp/IClpPackedMatrix.hpp
cylp/cpp/ICoinMP.cpp
cylp/cpp/CbcCompareUser.hpp
cylp/cpp/ICoinModel.hpp
cylp/cpp/IOsiCuts.cpp
cylp/cpp/IClpSimplexPrimal_Wolfe.cpp
cylp/cpp/IClpDualRowPivotBase.h
cylp/cpp/IClpSimplexPrimal.cpp
cylp/cpp/ICoinMpsIO.hpp
cylp/cpp/ICbcModel.cpp
cylp/cpp/CbcCompareUser.cpp
cylp/cpp/IClpPrimalColumnPivotBase.h
cylp/cpp/IOsiCuts.hpp
cylp/cpp/IClpDualRowPivotBase.cpp
cylp/cpp/IClpPrimalColumnPivot.h
cylp/cpp/IClpSimplexPrimal_Wolfe.hpp
