Metadata-Version: 2.4
Name: cylp
Version: 0.94.0
Summary: A Python interface for CLP, CBC, and CGL
Author-email: Mehdi Towhidi <mehdi.towhidi@gerad.ca>, Dominique Orban <dominique.orban@gerad.ca>, Ted Ralphs <ted@lehigh.edu>
License-Expression: EPL-2.0
Project-URL: Home Page, https://github.com/coin-or/CyLP
Project-URL: Documentation, https://coin-or.github.io/CyLP
License-File: LICENSE
License-File: AUTHORS
Requires-Dist: numpy>=1.26.0
Requires-Dist: scipy>=0.10.0
Dynamic: license-file
